somax/__init__.py
somax/settings.py
somax/classification/__init__.py
somax/classification/chroma_classifiers.py
somax/classification/classifier.py
somax/classification/pitch_classifiers.py
somax/classification/tables/__init__.py
somax/classification/tables/misc_hsom
somax/classification/tables/misc_hsom_c
somax/corpus_builder/__init__.py
somax/corpus_builder/chroma_filter.py
somax/corpus_builder/chromagram.py
somax/corpus_builder/corpus_builder.py
somax/corpus_builder/corpus_exporter.py
somax/corpus_builder/matrix_keys.py
somax/corpus_builder/midi_parser.py
somax/corpus_builder/note_matrix.py
somax/corpus_builder/note_matrix_utils.py
somax/corpus_builder/spectrogram.py
somax/features/__init__.py
somax/features/chroma_features.py
somax/features/energy_features.py
somax/features/feature.py
somax/features/pitch_features.py
somax/features/spectral_features.py
somax/features/virfun.py
somax/log/__init__.py
somax/log/logging.ini
somax/runtime/__init__.py
somax/runtime/activity_pattern.py
somax/runtime/agent.py
somax/runtime/asyncio_osc_object.py
somax/runtime/atom.py
somax/runtime/corpus.py
somax/runtime/corpus_event.py
somax/runtime/exceptions.py
somax/runtime/improvisation_memory.py
somax/runtime/influence.py
somax/runtime/label.py
somax/runtime/memory_spaces.py
somax/runtime/memory_state.py
somax/runtime/merge_actions.py
somax/runtime/osc_log_forwarder.py
somax/runtime/parameter.py
somax/runtime/peak_event.py
somax/runtime/peak_selector.py
somax/runtime/peaks.py
somax/runtime/player.py
somax/runtime/process_messages.py
somax/runtime/scale_actions.py
somax/runtime/streamview.py
somax/runtime/target.py
somax/runtime/transform_handler.py
somax/runtime/transforms.py
somax/scheduler/__init__.py
somax/scheduler/agent_scheduler.py
somax/scheduler/base_scheduler.py
somax/scheduler/scheduled_event.py
somax/scheduler/scheduled_object.py
somax/scheduler/transport.py
somax/utils/__init__.py
somax/utils/introspective.py
somax-0.1.2.dist-info/METADATA
somax-0.1.2.dist-info/WHEEL
somax-0.1.2.dist-info/top_level.txt
somax-0.1.2.dist-info/RECORD
