Metadata-Version: 2.1
Name: somax
Version: 0.1.2
Summary: Somax Library
Home-page: https://github.com/DYCI2/Somax2
Author: Joakim Borg
Author-email: joakim.borg@ircam.fr
License: GNU General Public License v3
Keywords: somax
Platform: UNKNOWN
Classifier: Development Status :: 2 - Pre-Alpha
Classifier: Intended Audience :: Developers
Classifier: License :: OSI Approved :: GNU General Public License v3 (GPLv3)
Classifier: Natural Language :: English
Classifier: Programming Language :: Python :: 3
Classifier: Programming Language :: Python :: 3.7
Classifier: Programming Language :: Python :: 3.8
Classifier: Programming Language :: Python :: 3.9
Requires-Python: >=3.7
Requires-Dist: numpy
Requires-Dist: scipy
Requires-Dist: maxosc
Requires-Dist: mido
Requires-Dist: scikit-learn
Requires-Dist: pandas
Requires-Dist: python-osc
Requires-Dist: matplotlib
